[
    {
        "year": 2021,
        "month": 4,
        "day": 12,
        "hour": 11,
        "minute": 0,
        "temp": [
            28.51272727272726,
            28.558124999999976,
            28.6,
            28.64757575757578,
            28.693750000000023
        ],
        "tds": [
            1222.4581818181816,
            1219.2587500000002,
            1218.6618181818171,
            1215.834242424242,
            1213.385
        ],
        "ph": [
            8.065151515151513,
            8.064375,
            8.033939393939391,
            8.017878787878786,
            7.9837500000000015
        ],
        "ntu": [
            3000.0,
            3000.0,
            3000.0,
            3000.0,
            3000.0
        ],
        "temp_avg": 28.602435606060613,
        "tds_avg": 1217.9195984848482,
        "ph_avg": 8.033018939393937,
        "ntu_avg": 3000.0
    },
    {
        "year": 2021,
        "month": 4,
        "day": 12,
        "hour": 11,
        "minute": 5,
        "temp": [
            28.75,
            28.78454545454543,
            28.809999999999974,
            28.87,
            28.923030303030327
        ],
        "tds": [
            1208.865151515151,
            1207.7763636363634,
            1207.0887500000003,
            1204.3206060606062,
            1201.038181818182
        ],
        "ph": [
            8.00030303030303,
            8.016363636363641,
            8.021875000000003,
            8.01787878787879,
            7.99969696969697
        ],
        "ntu": [
            3000.0,
            3000.0,
            3000.0,
            3000.0,
            3000.0
        ],
        "temp_avg": 28.827515151515144,
        "tds_avg": 1205.8178106060607,
        "ph_avg": 8.011223484848486,
        "ntu_avg": 3000.0
    },
    {
        "year": 2021,
        "month": 4,
        "day": 12,
        "hour": 11,
        "minute": 10,
        "temp": [
            28.941875000000024,
            29.0,
            29.049090909090886,
            29.069374999999983,
            29.12
        ],
        "tds": [
            1200.8081250000007,
            1201.5575757575755,
            1198.1409090909092,
            1197.5865625,
            1196.55
        ],
        "ph": [
            7.996250000000001,
            8.091515151515154,
            8.140606060606059,
            8.132812500000002,
            8.110000000000007
        ],
        "ntu": [
            3000.0,
            3000.0,
            3000.0,
            3000.0,
            3000.0
        ],
        "temp_avg": 29.036068181818177,
        "tds_avg": 1198.928634469697,
        "ph_avg": 8.094236742424243,
        "ntu_avg": 3000.0
    },
    {
        "year": 2021,
        "month": 4,
        "day": 12,
        "hour": 11,
        "minute": 15,
        "temp": [
            29.181515151515175,
            29.225625,
            29.24818181818182,
            29.299090909090886,
            29.323124999999987
        ],
        "tds": [
            1194.1348484848484,
            1355.5015625,
            1238.063333333334,
            1196.895757575757,
            1197.3493749999998
        ],
        "ph": [
            8.123939393939395,
            8.323125000000006,
            8.214242424242423,
            8.11424242424243,
            8.1203125
        ],
        "ntu": [
            3000.0,
            3000.0,
            3000.0,
            3000.0,
            3000.0
        ],
        "temp_avg": 29.25550757575757,
        "tds_avg": 1236.3889753787878,
        "ph_avg": 8.17917234848485,
        "ntu_avg": 3000.0
    },
    {
        "year": 2021,
        "month": 4,
        "day": 12,
        "hour": 11,
        "minute": 20,
        "temp": [
            29.37424242424243,
            29.4357575757576,
            29.454545454545467,
            29.501875,
            29.559999999999974
        ],
        "tds": [
            1194.5912121212114,
            1189.8533333333335,
            1179.1227272727276,
            1179.6015624999998,
            1176.1536363636367
        ],
        "ph": [
            8.100909090909092,
            8.13666666666666,
            8.13030303030303,
            8.019062499999999,
            7.967575757575756
        ],
        "ntu": [
            3000.0,
            3000.0,
            3000.0,
            3000.0,
            3000.0
        ],
        "temp_avg": 29.465284090909098,
        "tds_avg": 1183.8644943181819,
        "ph_avg": 8.070903409090906,
        "ntu_avg": 3000.0
    },
    {
        "year": 2021,
        "month": 4,
        "day": 12,
        "hour": 11,
        "minute": 25,
        "temp": [
            29.589090909090903,
            29.62,
            29.68363636363639,
            29.706363636363648,
            29.75
        ],
        "tds": [
            1177.3178787878794,
            1174.0668749999998,
            1173.6766666666665,
            1168.842727272727,
            1162.7993750000007
        ],
        "ph": [
            7.98454545454546,
            7.9740625000000005,
            7.97,
            7.97030303030303,
            7.97
        ],
        "ntu": [
            3000.0,
            3000.0,
            3000.0,
            3000.0,
            3000.0
        ],
        "temp_avg": 29.669818181818187,
        "tds_avg": 1171.3407045454546,
        "ph_avg": 7.973782196969698,
        "ntu_avg": 3000.0
    },
    {
        "year": 2021,
        "month": 4,
        "day": 12,
        "hour": 11,
        "minute": 30,
        "temp": [
            29.80636363636361,
            29.829999999999988,
            29.868125000000003,
            29.910303030303055,
            29.943636363636386
        ],
        "tds": [
            1162.8357575757575,
            1159.4512121212122,
            1153.4700000000005,
            1151.6881818181816,
            1150.7242424242427
        ],
        "ph": [
            7.957575757575754,
            7.9248484848484795,
            7.919999999999995,
            7.9130303030302995,
            7.947878787878791
        ],
        "ntu": [
            3000.0,
            3000.0,
            3000.0,
            3000.0,
            3000.0
        ],
        "temp_avg": 29.871685606060613,
        "tds_avg": 1155.633878787879,
        "ph_avg": 7.932666666666664,
        "ntu_avg": 3000.0
    },
    {
        "year": 2021,
        "month": 4,
        "day": 12,
        "hour": 11,
        "minute": 35,
        "temp": [
            29.986875,
            30.01235294117646,
            30.058181818181794,
            30.059999999999974,
            30.059999999999974
        ],
        "tds": [
            1149.2162500000009,
            1106.1697058823531,
            1034.5124242424245,
            1034.5375000000004,
            1033.6100000000004
        ],
        "ph": [
            7.942500000000002,
            7.93470588235294,
            7.784848484848484,
            7.7221874999999995,
            7.729090909090907
        ],
        "ntu": [
            3000.0,
            3000.0,
            3000.0,
            3000.0,
            3000.0
        ],
        "temp_avg": 30.03548195187164,
        "tds_avg": 1071.609176024956,
        "ph_avg": 7.8226665552584675,
        "ntu_avg": 3000.0
    },
    {
        "year": 2021,
        "month": 4,
        "day": 12,
        "hour": 11,
        "minute": 40,
        "temp": [
            30.059999999999974,
            30.059999999999974,
            30.04181818181817,
            30.0,
            30.0
        ],
        "tds": [
            1033.6100000000004,
            1033.7406250000004,
            1032.7345454545455,
            1035.7000000000005,
            1035.7000000000005
        ],
        "ph": [
            7.729393939393937,
            7.749374999999999,
            7.76757575757576,
            7.78,
            7.789999999999997
        ],
        "ntu": [
            3000.0,
            3000.0,
            3000.0,
            3000.0,
            3000.0
        ],
        "temp_avg": 30.032363636363623,
        "tds_avg": 1034.2970340909096,
        "ph_avg": 7.763268939393939,
        "ntu_avg": 3000.0
    },
    {
        "year": 2021,
        "month": 4,
        "day": 12,
        "hour": 11,
        "minute": 45,
        "temp": [
            29.956363636363662,
            29.940000000000026,
            29.922500000000014,
            29.872121212121215,
            29.86454545454545
        ],
        "tds": [
            1037.5366666666673,
            1037.7900000000006,
            1036.9909375000004,
            1039.9000000000005,
            1040.2196969696972
        ],
        "ph": [
            7.77606060606061,
            7.759393939393936,
            7.812500000000001,
            7.863636363636365,
            7.882121212121207
        ],
        "ntu": [
            3000.0,
            3000.0,
            3000.0,
            3000.0,
            3000.0
        ],
        "temp_avg": 29.911106060606073,
        "tds_avg": 1038.4874602272732,
        "ph_avg": 7.818742424242423,
        "ntu_avg": 3000.0
    },
    {
        "year": 2021,
        "month": 4,
        "day": 12,
        "hour": 11,
        "minute": 50,
        "temp": [
            29.813749999999974,
            29.809999999999974,
            29.764545454545456,
            29.75,
            29.730000000000018
        ],
        "tds": [
            1041.8121874999993,
            1040.4233333333327,
            1043.6160606060612,
            1043.7784375000008,
            1044.7418181818182
        ],
        "ph": [
            7.900000000000004,
            7.906969696969695,
            7.877878787878791,
            7.8365625,
            7.884545454545448
        ],
        "ntu": [
            3000.0,
            3000.0,
            3000.0,
            3000.0,
            3000.0
        ],
        "temp_avg": 29.773659090909085,
        "tds_avg": 1042.8743674242426,
        "ph_avg": 7.881191287878787,
        "ntu_avg": 3000.0
    },
    {
        "year": 2021,
        "month": 4,
        "day": 12,
        "hour": 11,
        "minute": 55,
        "temp": [
            29.690000000000026,
            29.687812500000025,
            29.622121212121215,
            29.62,
            29.569374999999976
        ],
        "tds": [
            1045.0066666666662,
            1046.3590624999997,
            1045.2509090909098,
            1046.4578787878797,
            1049.3343749999995
        ],
        "ph": [
            7.874242424242427,
            7.855312500000003,
            7.881212121212117,
            7.826969696969699,
            7.776875000000005
        ],
        "ntu": [
            3000.0,
            3000.0,
            3000.0,
            3000.0,
            3000.0
        ],
        "temp_avg": 29.637861742424246,
        "tds_avg": 1046.481778409091,
        "ph_avg": 7.84292234848485,
        "ntu_avg": 3000.0
    }
]