[
    {
        "year": 2021,
        "month": 4,
        "day": 8,
        "hour": 22,
        "minute": 0,
        "temp": [
            27.75,
            27.695454545454567,
            27.690000000000023,
            27.68787878787881,
            27.6369696969697
        ],
        "tds": [
            0.0,
            0.0,
            0.0,
            0.0,
            0.0
        ],
        "ph": [
            0.0,
            0.0,
            0.0,
            0.0,
            0.0
        ],
        "ntu": [
            3000.0,
            3000.0,
            3000.0,
            3000.0,
            3000.0
        ],
        "temp_avg": 27.692060606060625,
        "tds_avg": 0.0,
        "ph_avg": 0.0,
        "ntu_avg": 3000.0
    },
    {
        "year": 2021,
        "month": 4,
        "day": 8,
        "hour": 22,
        "minute": 5,
        "temp": [
            27.62,
            27.605454545454535,
            27.559999999999977,
            27.559999999999977,
            27.529090909090897
        ],
        "tds": [
            0.0,
            0.0,
            0.0,
            0.0,
            0.0
        ],
        "ph": [
            0.0,
            0.0,
            0.0,
            0.0,
            0.0
        ],
        "ntu": [
            3000.0,
            3000.0,
            3000.0,
            3000.0,
            3000.0
        ],
        "temp_avg": 27.57490909090908,
        "tds_avg": 0.0,
        "ph_avg": 0.0,
        "ntu_avg": 3000.0
    },
    {
        "year": 2021,
        "month": 4,
        "day": 8,
        "hour": 22,
        "minute": 10,
        "temp": [
            27.5,
            27.498125,
            27.447272727272747,
            27.440000000000023,
            27.43781250000002
        ],
        "tds": [
            0.0,
            0.0,
            0.0,
            0.0,
            0.0
        ],
        "ph": [
            0.0,
            0.0,
            0.0,
            0.0,
            0.0
        ],
        "ntu": [
            3000.0,
            3000.0,
            3000.0,
            3000.0,
            3000.0
        ],
        "temp_avg": 27.46464204545456,
        "tds_avg": 0.0,
        "ph_avg": 0.0,
        "ntu_avg": 3000.0
    },
    {
        "year": 2021,
        "month": 4,
        "day": 8,
        "hour": 22,
        "minute": 15,
        "temp": [
            27.397575757575762,
            27.37,
            27.37,
            27.32090909090907,
            27.309999999999977
        ],
        "tds": [
            0.0,
            0.0,
            0.0,
            0.0,
            0.0
        ],
        "ph": [
            0.0,
            0.0,
            0.0,
            0.0,
            0.0
        ],
        "ntu": [
            3000.0,
            3000.0,
            3000.0,
            3000.0,
            3000.0
        ],
        "temp_avg": 27.353696969696962,
        "tds_avg": 0.0,
        "ph_avg": 0.0,
        "ntu_avg": 3000.0
    },
    {
        "year": 2021,
        "month": 4,
        "day": 8,
        "hour": 22,
        "minute": 20,
        "temp": [
            27.304545454545437,
            27.255454545454544,
            27.25,
            27.24818181818182,
            27.193636363636386
        ],
        "tds": [
            0.0,
            0.0,
            0.0,
            0.0,
            0.0
        ],
        "ph": [
            0.0,
            0.0,
            0.0,
            0.0,
            0.0
        ],
        "ntu": [
            3000.0,
            3000.0,
            3000.0,
            3000.0,
            3000.0
        ],
        "temp_avg": 27.250363636363637,
        "tds_avg": 0.0,
        "ph_avg": 0.0,
        "ntu_avg": 3000.0
    },
    {
        "year": 2021,
        "month": 4,
        "day": 8,
        "hour": 22,
        "minute": 25,
        "temp": [
            27.190000000000023,
            27.18787878787881,
            27.134848484848487,
            27.12,
            27.12
        ],
        "tds": [
            0.0,
            0.0,
            0.0,
            0.0,
            0.0
        ],
        "ph": [
            0.0,
            0.0,
            0.0,
            0.0,
            0.0
        ],
        "ntu": [
            3000.0,
            3000.0,
            3000.0,
            3000.0,
            3000.0
        ],
        "temp_avg": 27.150545454545465,
        "tds_avg": 0.0,
        "ph_avg": 0.0,
        "ntu_avg": 3000.0
    },
    {
        "year": 2021,
        "month": 4,
        "day": 8,
        "hour": 22,
        "minute": 30,
        "temp": [
            27.086249999999982,
            27.059999999999977,
            27.059999999999977,
            27.024375,
            27.0
        ],
        "tds": [
            1.795,
            0.0,
            0.0,
            0.0,
            0.0
        ],
        "ph": [
            0.0,
            0.0,
            0.0,
            0.0,
            0.0
        ],
        "ntu": [
            3000.0,
            3000.0,
            3000.0,
            3000.0,
            3000.0
        ],
        "temp_avg": 27.04612499999999,
        "tds_avg": 0.359,
        "ph_avg": 0.0,
        "ntu_avg": 3000.0
    },
    {
        "year": 2021,
        "month": 4,
        "day": 8,
        "hour": 22,
        "minute": 35,
        "temp": [
            27.0,
            26.998125,
            26.98545454545456,
            26.972727272727283,
            27.0
        ],
        "tds": [
            0.0,
            145.5834375,
            1390.7257575757583,
            1383.9363636363644,
            1387.7500000000005
        ],
        "ph": [
            0.0,
            0.0,
            0.0,
            0.0,
            0.0
        ],
        "ntu": [
            3000.0,
            3000.0,
            3000.0,
            3000.0,
            3000.0
        ],
        "temp_avg": 26.99126136363637,
        "tds_avg": 861.5991117424246,
        "ph_avg": 0.0,
        "ntu_avg": 3000.0
    },
    {
        "year": 2021,
        "month": 4,
        "day": 8,
        "hour": 22,
        "minute": 40,
        "temp": [
            27.0,
            27.039999999999978,
            27.06187499999998,
            27.114545454545457,
            27.12424242424243
        ],
        "tds": [
            1386.2830303030314,
            1379.7121212121208,
            1378.6999999999996,
            1375.6727272727273,
            1374.9687878787875
        ],
        "ph": [
            0.0,
            0.0,
            0.0,
            0.0,
            0.0
        ],
        "ntu": [
            3000.0,
            3000.0,
            3000.0,
            3000.0,
            3000.0
        ],
        "temp_avg": 27.068132575757566,
        "tds_avg": 1379.0673333333334,
        "ph_avg": 0.0,
        "ntu_avg": 3000.0
    },
    {
        "year": 2021,
        "month": 4,
        "day": 8,
        "hour": 22,
        "minute": 45,
        "temp": [
            27.18781250000002,
            27.228181818181817,
            27.25363636363636,
            27.309999999999977,
            27.35181818181818
        ],
        "tds": [
            1370.9009374999998,
            1365.5190909090916,
            1363.4327272727276,
            1363.2781250000005,
            1353.8712121212125
        ],
        "ph": [
            0.0,
            0.0,
            0.0,
            0.0,
            0.0
        ],
        "ntu": [
            3000.0,
            3000.0,
            3000.0,
            3000.0,
            3000.0
        ],
        "temp_avg": 27.26628977272727,
        "tds_avg": 1363.4004185606063,
        "ph_avg": 0.0,
        "ntu_avg": 3000.0
    },
    {
        "year": 2021,
        "month": 4,
        "day": 8,
        "hour": 22,
        "minute": 50,
        "temp": [
            27.37424242424243,
            27.440000000000023,
            27.479999999999997,
            27.530909090909066,
            27.56187499999998
        ],
        "tds": [
            1346.8721212121206,
            1345.9125000000001,
            1342.5400000000002,
            1342.4693939393942,
            1345.4912500000003
        ],
        "ph": [
            0.0,
            0.0,
            0.0,
            0.0,
            0.0
        ],
        "ntu": [
            3000.0,
            3000.0,
            3000.0,
            3000.0,
            3000.0
        ],
        "temp_avg": 27.4774053030303,
        "tds_avg": 1344.6570530303031,
        "ph_avg": 0.0,
        "ntu_avg": 3000.0
    },
    {
        "year": 2021,
        "month": 4,
        "day": 8,
        "hour": 22,
        "minute": 55,
        "temp": [
            27.61818181818182,
            27.662424242424265,
            27.693750000000023,
            27.74818181818182,
            27.806363636363614
        ],
        "tds": [
            1346.6296969696966,
            1347.340606060607,
            1337.4056249999999,
            1331.351212121212,
            1332.9818181818175
        ],
        "ph": [
            0.0,
            0.0,
            0.0,
            0.0,
            0.0
        ],
        "ntu": [
            3000.0,
            3000.0,
            3000.0,
            3000.0,
            3000.0
        ],
        "temp_avg": 27.70578030303031,
        "tds_avg": 1339.1417916666664,
        "ph_avg": 0.0,
        "ntu_avg": 3000.0
    }
]